ansible/plugins/filter/ldif.py
ansible_filters_ldif-0.0.11.dist-info/AUTHORS
ansible_filters_ldif-0.0.11.dist-info/LICENSE
ansible_filters_ldif-0.0.11.dist-info/METADATA
ansible_filters_ldif-0.0.11.dist-info/WHEEL
ansible_filters_ldif-0.0.11.dist-info/top_level.txt
ansible_filters_ldif-0.0.11.dist-info/RECORD
