Metadata-Version: 2.1
Name: ansible-filters-ldif
Version: 0.0.11
Summary: Ansible filter to read or write LDIF.
Home-page: https://github.com/atterdag/ansible-filters-ldif
Author: Valdemar Lemche
Author-email: valdmar@lemche.net
License: GPLv3+
Project-URL: Bug Tracker, https://github.com/atterdag/ansible-filters-ldif/issues
Project-URL: Documentation, https://github.com/atterdag/ansible-filters-ldif/blob/master/README.rst
Project-URL: Source Code, https://github.com/atterdag/ansible-filters-ldif
Classifier: Development Status :: 5 - Production/Stable
Classifier: Environment :: Console
Classifier: Intended Audience :: Developers
Classifier: Intended Audience :: Information Technology
Classifier: Intended Audience :: System Administrators
Classifier: License :: OSI Approved :: GNU General Public License v3 or later (GPLv3+)
Classifier: Natural Language :: English
Classifier: Operating System :: POSIX
Classifier: Programming Language :: Python :: 2
Classifier: Programming Language :: Python :: 2.7
Classifier: Programming Language :: Python :: 3
Classifier: Programming Language :: Python :: 3.7
Classifier: Programming Language :: Python :: 3.8
Classifier: Programming Language :: Python :: 3.9
Classifier: Programming Language :: Python :: 3.10
Classifier: Topic :: System :: Installation/Setup
Classifier: Topic :: System :: Systems Administration
Classifier: Topic :: Utilities
License-File: LICENSE
License-File: AUTHORS
Requires-Dist: ansible (>=2.5.0)
Requires-Dist: python-ldap
